n3ml/__init__.py
n3ml/connection.py
n3ml/data.py
n3ml/encoder.py
n3ml/layer.py
n3ml/learning.py
n3ml/loss.py
n3ml/model.py
n3ml/network.py
n3ml/optimizer.py
n3ml/population.py
n3ml/serialization.py
n3ml/threshold.py
n3ml/util.py
n3ml/visualizer.py
n3ml_python-1.2.4.dist-info/LICENSE
n3ml_python-1.2.4.dist-info/METADATA
n3ml_python-1.2.4.dist-info/WHEEL
n3ml_python-1.2.4.dist-info/top_level.txt
n3ml_python-1.2.4.dist-info/RECORD
