Metadata-Version: 2.1
Name: n3ml-python
Version: 1.2.4
Summary: UNKNOWN
Home-page: UNKNOWN
Author: chatterboy
Author-email: chatter0502@gmail.com
License: UNKNOWN
Platform: UNKNOWN
License-File: LICENSE
Requires-Dist: matplotlib (==3.3.1)
Requires-Dist: numpy (==1.19.1)
Requires-Dist: scikit-learn (==0.24.1)
